exonware/__init__.py
exonware/xwnode/__init__.py
exonware/xwnode/add_strategy_types.py
exonware/xwnode/base.py
exonware/xwnode/config.py
exonware/xwnode/contracts.py
exonware/xwnode/defs.py
exonware/xwnode/errors.py
exonware/xwnode/facade.py
exonware/xwnode/version.py
exonware/xwnode/common/__init__.py
exonware/xwnode/common/graph/__init__.py
exonware/xwnode/common/graph/caching.py
exonware/xwnode/common/graph/contracts.py
exonware/xwnode/common/graph/errors.py
exonware/xwnode/common/graph/indexing.py
exonware/xwnode/common/graph/manager.py
exonware/xwnode/common/management/__init__.py
exonware/xwnode/common/management/manager.py
exonware/xwnode/common/management/migration.py
exonware/xwnode/common/monitoring/__init__.py
exonware/xwnode/common/monitoring/metrics.py
exonware/xwnode/common/monitoring/pattern_detector.py
exonware/xwnode/common/monitoring/performance_monitor.py
exonware/xwnode/common/patterns/__init__.py
exonware/xwnode/common/patterns/advisor.py
exonware/xwnode/common/patterns/flyweight.py
exonware/xwnode/common/patterns/registry.py
exonware/xwnode/common/utils/__init__.py
exonware/xwnode/common/utils/simple.py
exonware/xwnode/common/utils/utils.py
exonware/xwnode/edges/strategies/__init__.py
exonware/xwnode/edges/strategies/_base_edge.py
exonware/xwnode/edges/strategies/adj_list.py
exonware/xwnode/edges/strategies/adj_matrix.py
exonware/xwnode/edges/strategies/base.py
exonware/xwnode/edges/strategies/bidir_wrapper.py
exonware/xwnode/edges/strategies/bitemporal.py
exonware/xwnode/edges/strategies/block_adj_matrix.py
exonware/xwnode/edges/strategies/bv_graph.py
exonware/xwnode/edges/strategies/compressed_graph.py
exonware/xwnode/edges/strategies/coo.py
exonware/xwnode/edges/strategies/csc.py
exonware/xwnode/edges/strategies/csr.py
exonware/xwnode/edges/strategies/dynamic_adj_list.py
exonware/xwnode/edges/strategies/edge_list.py
exonware/xwnode/edges/strategies/edge_property_store.py
exonware/xwnode/edges/strategies/euler_tour.py
exonware_xwnode-0.0.1.26.dist-info/METADATA
exonware_xwnode-0.0.1.26.dist-info/WHEEL
exonware_xwnode-0.0.1.26.dist-info/licenses/LICENSE
exonware_xwnode-0.0.1.26.dist-info/RECORD
